Workbook

Sheet README
A1: Mock Quarterly Access Review (Practice Lab - ALL DATA IS FICTIONAL)
A3: Scenario | B3: You are the IAM analyst running the Q4 user access review for a fictional company. Compare the Access List (who has access to what) against the HR Roster (who actually works here and in what role), then decide whether each access should stay, go, or needs a justification.
A4: Review date | B4: 46313
A6: Your steps | B6: 1) Read the HR Roster. 2) Go through every row of the Access List. 3) Pick a Decision in the yellow column (dropdown). 4) Write a short Reviewer Comment explaining why. 5) Copy your issues into the Findings Log. 6) Check the Summary sheet.
A7: Decision options | B7: Keep = access matches the person's current job and status. Remove = access should be revoked. Needs Justification = you can't tell; the owner must explain or approve.
A8: What to look for | B8: Think about: people who left or changed jobs, access that is too powerful for the role, two permissions that should not be held by one person, accounts with no clear owner, access nobody is using, and access approved by the wrong person.
A9: Cells you edit | B9: Yellow cells only: Review date (below), Decision and Reviewer Comment on the Access List, and the Findings Log rows. Grey cells are formulas that pull data for you - do not type over them.
A10: Example (not real data) | B10: Example comment: 'HR shows this person moved to Marketing on 2026-08-15, but they still hold the Finance approver role. Remove; confirm with the Finance manager.' Example decision: Remove.
A11: Safety | B11: Everything here is made up. Do not add real employee names, real systems from your job, or anything from NIH or any employer.

Sheet HR Roster
A1: Employee ID | B1: Name | C1: Department | D1: Job Title | E1: Manager | F1: HR Status | G1: Status / Move Date | H1: HR Note
A2: E001 | B2: Dana Whitfield | C2: Finance | D2: Finance Manager | E2: Rhonda Diaz | F2: Active
A3: E002 | B3: Marcus Lee | C3: Finance | D3: AP Analyst | E3: Dana Whitfield | F3: Active
A4: E003 | B4: Priya Nair | C4: Finance | D4: Accounts Payable Lead | E4: Dana Whitfield | F4: Active
A5: E004 | B5: Tom Becker | C5: IT | D5: Systems Administrator | E5: Sam Ortiz | F5: Active
A6: E005 | B6: Sam Ortiz | C6: IT | D6: IT Manager | E6: Rhonda Diaz | F6: Active
A7: E006 | B7: Elena Ruiz | C7: Marketing | D7: Marketing Specialist | E7: Chris Hale | F7: Active | G7: 46249 | H7: Transferred from Finance to Marketing
A8: E007 | B8: Chris Hale | C8: Marketing | D8: Marketing Director | E8: Rhonda Diaz | F8: Active
A9: E008 | B9: Jordan Price | C9: Sales | D9: Sales Representative | E9: Maya Chen | F9: Terminated | G9: 46234 | H9: Employment ended
A10: E009 | B10: Maya Chen | C10: Sales | D10: Sales Manager | E10: Rhonda Diaz | F10: Active
A11: E010 | B11: Alex Kim | C11: IT | D11: Summer Intern | E11: Sam Ortiz | F11: Active | H11: Intern, started June 2026
A12: E011 | B12: Rosa Alvarez | C12: HR | D12: HR Generalist | E12: Ken Doyle | F12: Active
A13: E012 | B13: Ken Doyle | C13: HR | D13: HR Director | E13: Rhonda Diaz | F13: Active
A14: E013 | B14: Victor Shaw | C14: Operations | D14: Operations Analyst | E14: Lena Park | F14: Active
A15: E014 | B15: Lena Park | C15: Operations | D15: Operations Manager | E15: Rhonda Diaz | F15: Active
A16: E015 | B16: Nina Patel | C16: Sales | D16: Account Executive | E16: Maya Chen | F16: On Leave | G16: 46266 | H16: Leave began 2026-09-01, expected return 2027-01
A17: E016 | B17: Owen Brooks | C17: Finance | D17: Contractor (AP support) | E17: Dana Whitfield | F17: Contract Ended | G17: 46295 | H17: Contract ended

Sheet Access List
A1: Access ID | B1: Employee ID | C1: Employee Name (HR) | D1: Department (HR) | E1: HR Status (HR) | F1: System | G1: Role / Entitlement | H1: Privilege Level | I1: Granted Date | J1: Approved By | K1: Last Login | L1: Days Since Last Login | M1: Decision | N1: Reviewer Comment
A2: A001 | B2: E001 | C2: =IFERROR(INDEX('HR Roster'!$B$2:$B$17,MATCH($B2,'HR Roster'!$A$2:$A$17,0)),"NOT IN HR ROSTER") -> Dana Whitfield | D2: =IFERROR(INDEX('HR Roster'!$C$2:$C$17,MATCH($B2,'HR Roster'!$A$2:$A$17,0)),"NOT IN HR ROSTER") -> Finance | E2: =IFERROR(INDEX('HR Roster'!$F$2:$F$17,MATCH($B2,'HR Roster'!$A$2:$A$17,0)),"NOT IN HR ROSTER") -> Active | F2: Okta | G2: User | H2: Standard | I2: 44256 | J2: Sam Ortiz | K2: 46311 | L2: =README!$B$4-K2 -> 2 | M2: Keep | N2: Access matches current role and job responsibilities. Approved by manager.
A3: A002 | B3: E001 | C3: =IFERROR(INDEX('HR Roster'!$B$2:$B$17,MATCH($B3,'HR Roster'!$A$2:$A$17,0)),"NOT IN HR ROSTER") -> Dana Whitfield | D3: =IFERROR(INDEX('HR Roster'!$C$2:$C$17,MATCH($B3,'HR Roster'!$A$2:$A$17,0)),"NOT IN HR ROSTER") -> Finance | E3: =IFERROR(INDEX('HR Roster'!$F$2:$F$17,MATCH($B3,'HR Roster'!$A$2:$A$17,0)),"NOT IN HR ROSTER") -> Active | F3: Payment System | G3: Payment Approver | H3: Privileged | I3: 44256 | J3: Sam Ortiz | K3: 46310 | L3: =README!$B$4-K3 -> 3 | M3: Keep | N3: Access matches current role and job responsibilities. Approved by manager.
A4: A003 | B4: E002 | C4: =IFERROR(INDEX('HR Roster'!$B$2:$B$17,MATCH($B4,'HR Roster'!$A$2:$A$17,0)),"NOT IN HR ROSTER") -> Marcus Lee | D4: =IFERROR(INDEX('HR Roster'!$C$2:$C$17,MATCH($B4,'HR Roster'!$A$2:$A$17,0)),"NOT IN HR ROSTER") -> Finance | E4: =IFERROR(INDEX('HR Roster'!$F$2:$F$17,MATCH($B4,'HR Roster'!$A$2:$A$17,0)),"NOT IN HR ROSTER") -> Active | F4: Okta | G4: User | H4: Standard | I4: 44691 | J4: Dana Whitfield | K4: 46312 | L4: =README!$B$4-K4 -> 1 | M4: Keep | N4: Access matches current role and job responsibilities. Approved by manager.
A5: A004 | B5: E002 | C5: =IFERROR(INDEX('HR Roster'!$B$2:$B$17,MATCH($B5,'HR Roster'!$A$2:$A$17,0)),"NOT IN HR ROSTER") -> Marcus Lee | D5: =IFERROR(INDEX('HR Roster'!$C$2:$C$17,MATCH($B5,'HR Roster'!$A$2:$A$17,0)),"NOT IN HR ROSTER") -> Finance | E5: =IFERROR(INDEX('HR Roster'!$F$2:$F$17,MATCH($B5,'HR Roster'!$A$2:$A$17,0)),"NOT IN HR ROSTER") -> Active | F5: Payment System | G5: Invoice Entry | H5: Standard | I5: 44691 | J5: Dana Whitfield | K5: 46312 | L5: =README!$B$4-K5 -> 1 | M5: Keep | N5: Access matches current role and job responsibilities. Approved by manager.
A6: A005 | B6: E003 | C6: =IFERROR(INDEX('HR Roster'!$B$2:$B$17,MATCH($B6,'HR Roster'!$A$2:$A$17,0)),"NOT IN HR ROSTER") -> Priya Nair | D6: =IFERROR(INDEX('HR Roster'!$C$2:$C$17,MATCH($B6,'HR Roster'!$A$2:$A$17,0)),"NOT IN HR ROSTER") -> Finance | E6: =IFERROR(INDEX('HR Roster'!$F$2:$F$17,MATCH($B6,'HR Roster'!$A$2:$A$17,0)),"NOT IN HR ROSTER") -> Active | F6: Okta | G6: User | H6: Standard | I6: 44816 | J6: Dana Whitfield | K6: 46311 | L6: =README!$B$4-K6 -> 2 | M6: Keep | N6: Access matches current role and job responsibilities. Approved by manager.
A7: A006 | B7: E003 | C7: =IFERROR(INDEX('HR Roster'!$B$2:$B$17,MATCH($B7,'HR Roster'!$A$2:$A$17,0)),"NOT IN HR ROSTER") -> Priya Nair | D7: =IFERROR(INDEX('HR Roster'!$C$2:$C$17,MATCH($B7,'HR Roster'!$A$2:$A$17,0)),"NOT IN HR ROSTER") -> Finance | E7: =IFERROR(INDEX('HR Roster'!$F$2:$F$17,MATCH($B7,'HR Roster'!$A$2:$A$17,0)),"NOT IN HR ROSTER") -> Active | F7: Payment System | G7: Create Vendor | H7: Privileged | I7: 44938 | J7: Dana Whitfield | K7: 46309 | L7: =README!$B$4-K7 -> 4 | M7: Needs Justification | N7: Unable to confirm business need; requesting justification from manager by 10/25/2026
A8: A007 | B8: E003 | C8: =IFERROR(INDEX('HR Roster'!$B$2:$B$17,MATCH($B8,'HR Roster'!$A$2:$A$17,0)),"NOT IN HR ROSTER") -> Priya Nair | D8: =IFERROR(INDEX('HR Roster'!$C$2:$C$17,MATCH($B8,'HR Roster'!$A$2:$A$17,0)),"NOT IN HR ROSTER") -> Finance | E8: =IFERROR(INDEX('HR Roster'!$F$2:$F$17,MATCH($B8,'HR Roster'!$A$2:$A$17,0)),"NOT IN HR ROSTER") -> Active | F8: Payment System | G8: Approve Payment | H8: Privileged | I8: 45446 | J8: Dana Whitfield | K8: 46309 | L8: =README!$B$4-K8 -> 4 | M8: Needs Justification | N8: Unable to confirm business need; requesting justification from manager by 10/25/2026
A9: A008 | B9: E004 | C9: =IFERROR(INDEX('HR Roster'!$B$2:$B$17,MATCH($B9,'HR Roster'!$A$2:$A$17,0)),"NOT IN HR ROSTER") -> Tom Becker | D9: =IFERROR(INDEX('HR Roster'!$C$2:$C$17,MATCH($B9,'HR Roster'!$A$2:$A$17,0)),"NOT IN HR ROSTER") -> IT | E9: =IFERROR(INDEX('HR Roster'!$F$2:$F$17,MATCH($B9,'HR Roster'!$A$2:$A$17,0)),"NOT IN HR ROSTER") -> Active | F9: Okta | G9: Super Admin | H9: Privileged | I9: 43863 | J9: Sam Ortiz | K9: 46312 | L9: =README!$B$4-K9 -> 1 | M9: Keep | N9: Privileged access justified by role (Systems Administrator); approver is independent.
A10: A009 | B10: E004 | C10: =IFERROR(INDEX('HR Roster'!$B$2:$B$17,MATCH($B10,'HR Roster'!$A$2:$A$17,0)),"NOT IN HR ROSTER") -> Tom Becker | D10: =IFERROR(INDEX('HR Roster'!$C$2:$C$17,MATCH($B10,'HR Roster'!$A$2:$A$17,0)),"NOT IN HR ROSTER") -> IT | E10: =IFERROR(INDEX('HR Roster'!$F$2:$F$17,MATCH($B10,'HR Roster'!$A$2:$A$17,0)),"NOT IN HR ROSTER") -> Active | F10: AWS Console | G10: Administrator | H10: Privileged | I10: 44396 | J10: Sam Ortiz | K10: 46307 | L10: =README!$B$4-K10 -> 6 | M10: Keep | N10: Privileged access justified by role (Systems Administrator); approver is independent.
A11: A010 | B11: E005 | C11: =IFERROR(INDEX('HR Roster'!$B$2:$B$17,MATCH($B11,'HR Roster'!$A$2:$A$17,0)),"NOT IN HR ROSTER") -> Sam Ortiz | D11: =IFERROR(INDEX('HR Roster'!$C$2:$C$17,MATCH($B11,'HR Roster'!$A$2:$A$17,0)),"NOT IN HR ROSTER") -> IT | E11: =IFERROR(INDEX('HR Roster'!$F$2:$F$17,MATCH($B11,'HR Roster'!$A$2:$A$17,0)),"NOT IN HR ROSTER") -> Active | F11: Okta | G11: Super Admin | H11: Privileged | I11: 43717 | J11: Rhonda Diaz | K11: 46305 | L11: =README!$B$4-K11 -> 8 | M11: Keep | N11: Access matches current role and job responsibilities. Approved by manager.
A12: A011 | B12: E006 | C12: =IFERROR(INDEX('HR Roster'!$B$2:$B$17,MATCH($B12,'HR Roster'!$A$2:$A$17,0)),"NOT IN HR ROSTER") -> Elena Ruiz | D12: =IFERROR(INDEX('HR Roster'!$C$2:$C$17,MATCH($B12,'HR Roster'!$A$2:$A$17,0)),"NOT IN HR ROSTER") -> Marketing | E12: =IFERROR(INDEX('HR Roster'!$F$2:$F$17,MATCH($B12,'HR Roster'!$A$2:$A$17,0)),"NOT IN HR ROSTER") -> Active | F12: Okta | G12: User | H12: Standard | I12: 45342 | J12: Chris Hale | K12: 46312 | L12: =README!$B$4-K12 -> 1 | M12: Keep | N12: Access matches current role and job responsibilities. Approved by manager.
A13: A012 | B13: E006 | C13: =IFERROR(INDEX('HR Roster'!$B$2:$B$17,MATCH($B13,'HR Roster'!$A$2:$A$17,0)),"NOT IN HR ROSTER") -> Elena Ruiz | D13: =IFERROR(INDEX('HR Roster'!$C$2:$C$17,MATCH($B13,'HR Roster'!$A$2:$A$17,0)),"NOT IN HR ROSTER") -> Marketing | E13: =IFERROR(INDEX('HR Roster'!$F$2:$F$17,MATCH($B13,'HR Roster'!$A$2:$A$17,0)),"NOT IN HR ROSTER") -> Active | F13: Payment System | G13: Payment Approver | H13: Privileged | I13: 45342 | J13: Dana Whitfield | K13: 46267 | L13: =README!$B$4-K13 -> 46 | M13: Remove | N13: User transferred departments on 08/15/2026; access from prior role no longer needed.
... A35: A034 | B35: E016 | C35: =IFERROR(INDEX('HR Roster'!$B$2:$B$17,MATCH($B35,'HR Roster'!$A$2:$A$17,0)),"NOT IN HR ROSTER") -> Owen Brooks | D35: =IFERROR(INDEX('HR Roster'!$C$2:$C$17,MATCH($B35,'HR Roster'!$A$2:$A$17,0)),"NOT IN HR ROSTER") -> Finance | E35: =IFERROR(INDEX('HR Roster'!$F$2:$F$17,MATCH($B35,'HR Roster'!$A$2:$A$17,0)),"NOT IN HR ROSTER") -> Contract Ended | F35: Payment System | G35: Invoice Entry | H35: Standard | I35: 45566 | J35: Dana Whitfield | K35: 46295 | L35: =README!$B$4-K35 -> 18 | M35: Remove | N35: Contract ended 09/30/2026 access no longer required.
A36: A035 | B36: SVC-01 | C36: =IFERROR(INDEX('HR Roster'!$B$2:$B$17,MATCH($B36,'HR Roster'!$A$2:$A$17,0)),"NOT IN HR ROSTER") -> NOT IN HR ROSTER | D36: =IFERROR(INDEX('HR Roster'!$C$2:$C$17,MATCH($B36,'HR Roster'!$A$2:$A$17,0)),"NOT IN HR ROSTER") -> NOT IN HR ROSTER | E36: =IFERROR(INDEX('HR Roster'!$F$2:$F$17,MATCH($B36,'HR Roster'!$A$2:$A$17,0)),"NOT IN HR ROSTER") -> NOT IN HR ROSTER | F36: AWS Console | G36: Administrator (shared account svc_admin_shared) | H36: Privileged | I36: 43480 | K36: 46312 | L36: =README!$B$4-K36 -> 1 | M36: Remove | N36: it’s a shared privileged account, so no one person is accountable for it.

Sheet Findings Log
A1: Finding # | B1: Access ID(s) | C1: Person / Account | D1: What is wrong | E1: Risk (High/Med/Low) | F1: Recommended action | G1: Owner to contact | H1: Status
A2: EXAMPLE | B2: A000 | C2: Example Person (not in data) | D2: Moved departments but kept the old department's approver role | E2: High | F2: Remove the old role; confirm with the former manager | G2: Former department manager | H2: Open
A3: 1 | B3: A015, A016, A017 | C3: Jordan Price (E008) | D3: Terminated on 07/31/2026 but Okta, M365, and Salesforce access remain active. Okta shows login on 10/05/2026 | E3: High | F3: Disable all accounts now and notify security to review the post termination login | G3: Maya Chen (Former Manager) | H3: Open
A4: 2 | B4: A012, A013 | C4: Elena Ruiz (E006) | D4: Transferred from Finance to Marketing on 08/15/2026 but still holds Payment Approver (privileged) and Finance Share read/write. Payment Approver was last used 09/02/2026, after the transfer. Policy rule 3 requires old-role access to be removed. | E4: High | F4: Remove both entitlements and review payments she approved after 08/15/2026 | G4: Dana Whitfield | H4: Open
A5: 3 | B5: A006, A007 | C5: Priya Nair (E003) | D5: Holds both Create Vendor and Approve Payment in the Payment System, both privileged. One person can create a vendor and approve payment to it, which violates the segregation of duties rule | E5: High | F5: Remove one of the two entitlements, or require documented justification and a compensating control from the manager | G5: Dana Whitfield | H5: Open
A6: 4 | B6: A021 | C6: Alex Kim (E010) | D6: Summer Intern holds AWS Console Administrator (privileged). Policy rule 8 says interns get no administrator access. The access was approved by Tom Becker, a peer, and not by Alex’s manager (Sam Ortiz). | E6: High | F6: Remove administrator access and replace it with the minimum access needed for the internship | G6: Sam Ortiz (Alex’s manager) | H6: Open
A7: 5 | B7: A025 | C7: Ken Doyle (E012) | D7: Workday HR Administrator (privileged) was approved by Ken Doyle himself. Policy rule 4 says no one may approve their own access. | E7: High | F7: Get independent approval from his manager; remove the access if it isn’t given | G7: Rhonda Diaz (Ken’s manager) | H7: Open
A8: 6 | B8: A027 | C8: Victor Shaw (E013) | D8: ServiceNow Admin (privileged) last used 02/10/2026, 250 days before the review date. Policy rule 5 says privileged access unused for 90 days or more should be removed. | E8: Medium | F8: Remove the admin role; Victor keeps his standard Okta access | G8: Lena Park (approver and manager) | H8: Open
A9: 7 | B9: A035 | C9: svc_admin_shared (SVC-01) | D9: Shared AWS Console Administrator (privileged) account has no named owner or approver and doesn’t appear in the HR Roster. Policy rule 6 requires a named owner and approver, and with no owner nobody is accountable for its actions. | E9: High | F9: Assign an owner, document the business need, rotate the credentials, and replace the shared account with named accounts if possible | G9: Sam Ortiz (IT Manager) to assign an owner | H9: Open
A10: 8 | B10: A030, A031 | C10: Nina Patel (E015) | D10: On approved leave since 09/01/2026, expected back 01/2027. Her access is standard only. Policy rule 9 lets standard access stay during leave, and nothing indicates misuse. | E10: Low | F10: No removal needed; confirm access is re-reviewed before her return | G10: Maya Chen (manager) | H10: Open
A11: 9 | B11: A032, A033, A034 | C11: Owen Brooks (E016) | D11: Contract ended 09/30/2026 per HR but Okta, Finance Share, and Invoice Entry are still active. Policy rule 2 requires removal within 1 business day. | E11: Medium | F11: Disable all three accounts | G11: Dana Whitfield | H11: Open
A12: 10
A13: 11
A14: 12

Sheet Summary
A1: Review Summary (updates automatically as you fill in Decisions)
A3: Decision | B3: Count | C3: % of reviewed
A4: Keep | B4: =COUNTIF('Access List'!$M$2:$M$36,A4) -> 21 | C4: =IF($B$7=0,0,B4/$B$7) -> 0.6
A5: Remove | B5: =COUNTIF('Access List'!$M$2:$M$36,A5) -> 11 | C5: =IF($B$7=0,0,B5/$B$7) -> 0.31428571
A6: Needs Justification | B6: =COUNTIF('Access List'!$M$2:$M$36,A6) -> 3 | C6: =IF($B$7=0,0,B6/$B$7) -> 0.085714286
A7: Total reviewed | B7: =SUM(B4:B6) -> 35
A8: Total access rows | B8: =COUNTA('Access List'!$A$2:$A$36) -> 35
A9: Still to review | B9: =B8-B7 -> 0
A11: Decisions by system
A12: System | B12: Keep | C12: Remove | D12: Needs Justification | E12: Privileged rows
A13: Okta | B13: =COUNTIFS('Access List'!$F$2:$F$36,$A13,'Access List'!$M$2:$M$36,"Keep") -> 14 | C13: =COUNTIFS('Access List'!$F$2:$F$36,$A13,'Access List'!$M$2:$M$36,"Remove") -> 2 | D13: =COUNTIFS('Access List'!$F$2:$F$36,$A13,'Access List'!$M$2:$M$36,"Needs Justification") -> 0 | E13: =COUNTIFS('Access List'!$F$2:$F$36,$A13,'Access List'!$H$2:$H$36,"Privileged") -> 2
A14: Payment System | B14: =COUNTIFS('Access List'!$F$2:$F$36,$A14,'Access List'!$M$2:$M$36,"Keep") -> 2 | C14: =COUNTIFS('Access List'!$F$2:$F$36,$A14,'Access List'!$M$2:$M$36,"Remove") -> 2 | D14: =COUNTIFS('Access List'!$F$2:$F$36,$A14,'Access List'!$M$2:$M$36,"Needs Justification") -> 2 | E14: =COUNTIFS('Access List'!$F$2:$F$36,$A14,'Access List'!$H$2:$H$36,"Privileged") -> 4
A15: AWS Console | B15: =COUNTIFS('Access List'!$F$2:$F$36,$A15,'Access List'!$M$2:$M$36,"Keep") -> 1 | C15: =COUNTIFS('Access List'!$F$2:$F$36,$A15,'Access List'!$M$2:$M$36,"Remove") -> 2 | D15: =COUNTIFS('Access List'!$F$2:$F$36,$A15,'Access List'!$M$2:$M$36,"Needs Justification") -> 0 | E15: =COUNTIFS('Access List'!$F$2:$F$36,$A15,'Access List'!$H$2:$H$36,"Privileged") -> 3
A16: Finance Share | B16: =COUNTIFS('Access List'!$F$2:$F$36,$A16,'Access List'!$M$2:$M$36,"Keep") -> 0 | C16: =COUNTIFS('Access List'!$F$2:$F$36,$A16,'Access List'!$M$2:$M$36,"Remove") -> 2 | D16: =COUNTIFS('Access List'!$F$2:$F$36,$A16,'Access List'!$M$2:$M$36,"Needs Justification") -> 0 | E16: =COUNTIFS('Access List'!$F$2:$F$36,$A16,'Access List'!$H$2:$H$36,"Privileged") -> 0
A17: Microsoft 365 | B17: =COUNTIFS('Access List'!$F$2:$F$36,$A17,'Access List'!$M$2:$M$36,"Keep") -> 0 | C17: =COUNTIFS('Access List'!$F$2:$F$36,$A17,'Access List'!$M$2:$M$36,"Remove") -> 1 | D17: =COUNTIFS('Access List'!$F$2:$F$36,$A17,'Access List'!$M$2:$M$36,"Needs Justification") -> 0 | E17: =COUNTIFS('Access List'!$F$2:$F$36,$A17,'Access List'!$H$2:$H$36,"Privileged") -> 0
A18: Salesforce CRM | B18: =COUNTIFS('Access List'!$F$2:$F$36,$A18,'Access List'!$M$2:$M$36,"Keep") -> 2 | C18: =COUNTIFS('Access List'!$F$2:$F$36,$A18,'Access List'!$M$2:$M$36,"Remove") -> 1 | D18: =COUNTIFS('Access List'!$F$2:$F$36,$A18,'Access List'!$M$2:$M$36,"Needs Justification") -> 0 | E18: =COUNTIFS('Access List'!$F$2:$F$36,$A18,'Access List'!$H$2:$H$36,"Privileged") -> 0
A19: Workday | B19: =COUNTIFS('Access List'!$F$2:$F$36,$A19,'Access List'!$M$2:$M$36,"Keep") -> 1 | C19: =COUNTIFS('Access List'!$F$2:$F$36,$A19,'Access List'!$M$2:$M$36,"Remove") -> 0 | D19: =COUNTIFS('Access List'!$F$2:$F$36,$A19,'Access List'!$M$2:$M$36,"Needs Justification") -> 1 | E19: =COUNTIFS('Access List'!$F$2:$F$36,$A19,'Access List'!$H$2:$H$36,"Privileged") -> 1
A20: ServiceNow | B20: =COUNTIFS('Access List'!$F$2:$F$36,$A20,'Access List'!$M$2:$M$36,"Keep") -> 1 | C20: =COUNTIFS('Access List'!$F$2:$F$36,$A20,'Access List'!$M$2:$M$36,"Remove") -> 1 | D20: =COUNTIFS('Access List'!$F$2:$F$36,$A20,'Access List'!$M$2:$M$36,"Needs Justification") -> 0 | E20: =COUNTIFS('Access List'!$F$2:$F$36,$A20,'Access List'!$H$2:$H$36,"Privileged") -> 1
A22: Note: 'Privileged rows' counts all privileged entitlements per system regardless of your decision.
